[
  {
    "card_index": 1,
    "hint": "",
    "question": "eat",
    "answer": "verb行为动词"
  },
  {
    "card_index": 2,
    "hint": "",
    "question": "a",
    "answer": "article冠词"
  },
  {
    "card_index": 3,
    "hint": "",
    "question": "rabbit",
    "answer": "noun名词"
  },
  {
    "card_index": 4,
    "hint": "",
    "question": "am",
    "answer": "beverb Be动词"
  },
  {
    "card_index": 5,
    "hint": "",
    "question": "like",
    "answer": "verb 行为动词"
  },
  {
    "card_index": 6,
    "hint": "",
    "question": "an",
    "answer": "article冠词"
  },
  {
    "card_index": 7,
    "hint": "",
    "question": "happy",
    "answer": "adjective形容词"
  },
  {
    "card_index": 8,
    "hint": "",
    "question": "open",
    "answer": "verb行为动词"
  },
  {
    "card_index": 9,
    "hint": "",
    "question": "the",
    "answer": "article冠词"
  },
  {
    "card_index": 10,
    "hint": "",
    "question": "beautiful",
    "answer": "adjective形容词"
  }
]
