[
  {
    "card_index": 1,
    "hint": "",
    "question": "结果状语从句中so…that的中文是什么意思？",
    "answer": "如此以至于"
  },
  {
    "card_index": 2,
    "hint": "",
    "question": "哪个连词和so…that意思是一样的？",
    "answer": "such…that"
  },
  {
    "card_index": 3,
    "hint": "",
    "question": "so是什么词性？",
    "answer": "adv."
  },
  {
    "card_index": 4,
    "hint": "",
    "question": "such是什么词性？",
    "answer": "adj."
  },
  {
    "card_index": 5,
    "hint": "",
    "question": "所以so…that里边的…跟在so后面需要用什么词性？",
    "answer": "adj."
  },
  {
    "card_index": 6,
    "hint": "",
    "question": "请举一个例子so…",
    "answer": "so bad"
  },
  {
    "card_index": 7,
    "hint": "",
    "question": "那么such…that后面的…需要用什么词性?",
    "answer": "noun或者黄头三人组"
  },
  {
    "card_index": 8,
    "hint": "",
    "question": "请举一个例子such什么?",
    "answer": "such a bad person"
  }
]