[
  {
    "card_index": 1,
    "hint": "Some shells can be used to hold water.",
    "question": "Shell",
    "answer": "贝壳"
  },
  {
    "card_index": 2,
    "hint": "He rowed across the river.",
    "question": "River",
    "answer": "河"
  },
  {
    "card_index": 3,
    "hint": "He fell into the lake.",
    "question": "Lake",
    "answer": "湖"
  },
  {
    "card_index": 4,
    "hint": "The mountain is two thousand meters high.",
    "question": "Mountain",
    "answer": "山，山脉"
  },
  {
    "card_index": 5,
    "hint": "We are going to climb a hill tomorrow.",
    "question": "Hill",
    "answer": "小山"
  },
  {
    "card_index": 6,
    "hint": "We play football on the grass.",
    "question": "Grass",
    "answer": "草坪"
  },
  {
    "card_index": 7,
    "hint": "You shouldn't sit on the ground.",
    "question": "Ground",
    "answer": "地面，土地，土壤"
  },
  {
    "card_index": 8,
    "hint": "In the desert, some people travel by camel.",
    "question": "Desert",
    "answer": "沙漠"
  }
]