[
  {
    "card_index": 1,
    "hint": "行为动词",
    "question": "enter",
    "answer": "进入，报名参加"
  },
  {
    "card_index": 2,
    "hint": "名词",
    "question": "rent",
    "answer": "租金"
  },
  {
    "card_index": 3,
    "hint": "行为动词",
    "question": "rent",
    "answer": "租借"
  },
  {
    "card_index": 4,
    "hint": "及物动词",
    "question": "rent",
    "answer": "出租，租用"
  },
  {
    "card_index": 5,
    "hint": "及物动词",
    "question": "invent",
    "answer": "发明，创造，捏造，虚构"
  },
  {
    "card_index": 6,
    "hint": "名词",
    "question": "talent",
    "answer": "才能，天才，天资"
  },
  {
    "card_index": 7,
    "hint": "形容词",
    "question": "absent",
    "answer": "缺席的，心不在焉的"
  },
  {
    "card_index": 8,
    "hint": "及物动词",
    "question": "absent",
    "answer": "使缺席"
  },
  {
    "card_index": 9,
    "hint": "名词",
    "question": "present",
    "answer": "礼物，现在"
  },
  {
    "card_index": 10,
    "hint": "形容词",
    "question": "present",
    "answer": "出席的，现在的"
  },
  {
    "card_index": 11,
    "hint": "行为动词",
    "question": "present",
    "answer": "提出，赠送，呈现"
  },
  {
    "card_index": 12,
    "hint": "名词",
    "question": "accident",
    "answer": "意外的事，事故"
  },
  {
    "card_index": 13,
    "hint": "形容词",
    "question": "confident",
    "answer": "确信的，有信心的，自信的"
  },
  {
    "card_index": 14,
    "hint": "名词",
    "question": "agent",
    "answer": "代理人，经纪人"
  },
  {
    "card_index": 15,
    "hint": "形容词",
    "question": "ancient",
    "answer": "古代的，古老的"
  },
  {
    "card_index": 16,
    "hint": "形容词",
    "question": "patient",
    "answer": "耐心的，忍耐的"
  },
  {
    "card_index": 17,
    "hint": "名词",
    "question": "patient",
    "answer": "病人"
  },
  {
    "card_index": 18,
    "hint": "形容词",
    "question": "convenient",
    "answer": "便利的，方便的"
  },
  {
    "card_index": 19,
    "hint": "名词",
    "question": "ingredient",
    "answer": "原料，要素，组成部分"
  },
  {
    "card_index": 20,
    "hint": "形容词",
    "question": "ingredient",
    "answer": "构成组成部分的"
  },
  {
    "card_index": 21,
    "hint": "形容词",
    "question": "best",
    "answer": "最好的"
  },
  {
    "card_index": 22,
    "hint": "副词",
    "question": "best",
    "answer": "最好"
  },
  {
    "card_index": 23,
    "hint": "名词",
    "question": "best",
    "answer": "最佳，至善"
  },
  {
    "card_index": 24,
    "hint": "名词",
    "question": "rest",
    "answer": "休息，剩余部分，其余的人或物"
  },
  {
    "card_index": 25,
    "hint": "不及物动词",
    "question": "rest",
    "answer": "休息"
  },
  {
    "card_index": 26,
    "hint": "名词",
    "question": "test",
    "answer": "测验"
  },
  {
    "card_index": 27,
    "hint": "及物动词",
    "question": "test",
    "answer": "测验，考查，实验"
  },
  {
    "card_index": 28,
    "hint": "及物动词",
    "question": "contest",
    "answer": "争辩，提出质疑"
  },
  {
    "card_index": 29,
    "hint": "不及物动词",
    "question": "contest",
    "answer": "竞争"
  },
  {
    "card_index": 30,
    "hint": "名词",
    "question": "contest",
    "answer": "竞赛，争夺"
  },
  {
    "card_index": 31,
    "hint": "名词",
    "question": "nest",
    "answer": "巢"
  },
  {
    "card_index": 32,
    "hint": "及物动词",
    "question": "nest",
    "answer": "为什么什么筑巢，嵌入"
  },
  {
    "card_index": 33,
    "hint": "不及物动词",
    "question": "nest",
    "answer": "筑巢，寻找鸟巢"
  },
  {
    "card_index": 34,
    "hint": "名词",
    "question": "west",
    "answer": "西，西方"
  },
  {
    "card_index": 35,
    "hint": "副词或形容词",
    "question": "west",
    "answer": "在西部的"
  },
  {
    "card_index": 36,
    "hint": "及物动词",
    "question": "invest",
    "answer": "投资，覆盖，耗费"
  },
  {
    "card_index": 37,
    "hint": "不及物动词",
    "question": "invest",
    "answer": "投资，入股"
  },
  {
    "card_index": 38,
    "hint": "及物动词",
    "question": "suggest",
    "answer": "建议，暗示"
  },
  {
    "card_index": 39,
    "hint": "形容词",
    "question": "honest",
    "answer": "诚实的，可靠的，正直的"
  },
  {
    "card_index": 40,
    "hint": "形容词",
    "question": "modest",
    "answer": "谦虚的，适度的"
  },
  {
    "card_index": 41,
    "hint": "名词",
    "question": "interest",
    "answer": "兴趣，利益，爱好，好处，利息"
  },
  {
    "card_index": 42,
    "hint": "及物动词",
    "question": "interest",
    "answer": "使有兴趣，引起什么什么注意"
  },
  {
    "card_index": 43,
    "hint": "名词",
    "question": "dish",
    "answer": "盘，碟，一道菜"
  },
  {
    "card_index": 44,
    "hint": "名词",
    "question": "fish",
    "answer": "鱼，鱼肉"
  },
  {
    "card_index": 45,
    "hint": "不及物动词",
    "question": "fish",
    "answer": "捕鱼，钓鱼"
  },
  {
    "card_index": 46,
    "hint": "行为动词",
    "question": "finish",
    "answer": "结束，完成"
  },
  {
    "card_index": 47,
    "hint": "名词",
    "question": "wish",
    "answer": "愿望，祝愿"
  },
  {
    "card_index": 48,
    "hint": "行为动词",
    "question": "wish",
    "answer": "想要"
  },
  {
    "card_index": 49,
    "hint": "及物动词",
    "question": "wish",
    "answer": "希望"
  },
  {
    "card_index": 50,
    "hint": "名词",
    "question": "rubbish",
    "answer": "废物，垃圾"
  },
  {
    "card_index": 51,
    "hint": "行为动词",
    "question": "relish",
    "answer": "享受，从什么什么中获得乐趣，品味"
  },
  {
    "card_index": 52,
    "hint": "名词",
    "question": "relish",
    "answer": "滋味，爱好，调味品"
  },
  {
    "card_index": 53,
    "hint": "行为动词",
    "question": "establish",
    "answer": "建立，确立，创办"
  }
]